pseudo_opendns.py
pseudo_opendns-0.1.0.dist-info/WHEEL
pseudo_opendns-0.1.0.dist-info/METADATA
pseudo_opendns-0.1.0.dist-info/RECORD
