Metadata-Version: 2.1
Name: pseudo-opendns
Version: 0.1.0
Summary: 
Author: Your Name
Author-email: you@example.com
Requires-Python: >=3.8,<4.0
Classifier: Programming Language :: Python :: 3
Classifier: Programming Language :: Python :: 3.10
Classifier: Programming Language :: Python :: 3.8
Classifier: Programming Language :: Python :: 3.9
Requires-Dist: dnslib (>=0.9.19,<0.10.0)
Requires-Dist: python-dotenv (>=0.20.0,<0.21.0)
